flask_svelte/__init__.py
flask_svelte/__main__.py
flask_svelte/data/sample-app.py
flask_svelte/data/sample-package.json
flask_svelte/data/sample-rollup.config.js
flask_svelte/data/sample-tailwind.config.js
flask_svelte/data/svelte-app/App.svelte
flask_svelte/data/svelte-app/main.js
flask_svelte/data/template.html
flask_svelte/main.py
LICENSE
flask_svelte-1.0.1.dist-info/entry_points.txt
flask_svelte-1.0.1.dist-info/LICENSE
flask_svelte-1.0.1.dist-info/METADATA
flask_svelte-1.0.1.dist-info/WHEEL
flask_svelte-1.0.1.dist-info/RECORD
