Metadata-Version: 2.1
Name: flask-svelte
Version: 1.0.1
Summary: A python package to create flask project with svelte frontend.
Home-page: https://github.com/priyanshu-shubham/flask-svelte
License: MIT
Keywords: flask,svelte,sveltekit,flask-svelte,flask-svelte-cli,flask-svelte-generator,flask-svelte-template
Author: Priyanshu Shubham
Author-email: priyanshushubham27@gmail.com
Requires-Python: >=3.8,<4.0
Classifier: License :: OSI Approved :: MIT License
Classifier: Programming Language :: Python :: 3
Classifier: Programming Language :: Python :: 3.8
Classifier: Programming Language :: Python :: 3.9
Classifier: Programming Language :: Python :: 3.10
Classifier: Programming Language :: Python :: 3.11
Classifier: Programming Language :: Python :: 3.12
Requires-Dist: click (>=8.1.7,<9.0.0)
Requires-Dist: flask (>=3.0.1,<4.0.0)
Project-URL: Repository, https://github.com/priyanshu-shubham/flask-svelte
